[
  {
    "reddit_title": "The Ghost in the Shell • Koukaku Kidoutai (TV) - Episode 3 discussion",
    "matched_anime_id": 177699,
    "matched_anime_native": "攻殻機動隊 THE GHOST IN THE SHELL",
    "score": 100.0,
    "num_comments": 164,
    "url": "https://www.reddit.com/r/anime/comments/1v2kdz4/the_ghost_in_the_shell_koukaku_kidoutai_tv/",
    "seasonYear": 2026,
    "season": "SUMMER"
  },
  {
    "reddit_title": "Jaadugar: A Witch in Mongolia - Episode 1: Sitara teasing Muhammed",
    "matched_anime_id": 190569,
    "matched_anime_native": "天幕のジャードゥーガル",
    "score": 100.0,
    "num_comments": 29,
    "url": "https://v.redd.it/vygfhqoq6leh1",
    "seasonYear": 2026,
    "season": "SUMMER"
  },
  {
    "reddit_title": "\"I used to be a tomboy\" [Tefuda Ga Oome No Victoria/Victoria of Many Faces]",
    "matched_anime_id": 198709,
    "matched_anime_native": "手札が多めのビクトリア",
    "score": 100.0,
    "num_comments": 24,
    "url": "https://v.redd.it/wm6leotkzleh1",
    "seasonYear": 2026,
    "season": "SUMMER"
  },
  {
    "reddit_title": "I Want to Love You Till Your Dying Day • Kimi ga Shinu made Koi wo Shitai - Episode 3 discussion",
    "matched_anime_id": 187260,
    "matched_anime_native": "きみが死ぬまで恋をしたい",
    "score": 100.0,
    "num_comments": 146,
    "url": "https://www.reddit.com/r/anime/comments/1v2h4xc/i_want_to_love_you_till_your_dying_day_kimi_ga/",
    "seasonYear": 2026,
    "season": "SUMMER"
  },
  {
    "reddit_title": "Young Ladies Don’t Play Fighting Games • Tai-Ari deshita. Ojou-sama wa Kakutou Game Nante Shinai - Episode 3 discussion",
    "matched_anime_id": 128757,
    "matched_anime_native": "対ありでした。 ～お嬢さまは格闘ゲームなんてしない～",
    "score": 100.0,
    "num_comments": 146,
    "url": "https://www.reddit.com/r/anime/comments/1v2froc/young_ladies_dont_play_fighting_games_taiari/",
    "seasonYear": 2026,
    "season": "SUMMER"
  },
  {
    "reddit_title": "Victoria of Many Faces • Tefuda ga Oome no Victoria - Episode 3 discussion",
    "matched_anime_id": 198709,
    "matched_anime_native": "手札が多めのビクトリア",
    "score": 100.0,
    "num_comments": 105,
    "url": "https://www.reddit.com/r/anime/comments/1v2l2vf/victoria_of_many_faces_tefuda_ga_oome_no_victoria/",
    "seasonYear": 2026,
    "season": "SUMMER"
  },
  {
    "reddit_title": "Red River • Sora wa Akai Kawa no Hotori - Episode 3 discussion",
    "matched_anime_id": 207809,
    "matched_anime_native": "天は赤い河のほとり",
    "score": 100.0,
    "num_comments": 46,
    "url": "https://www.reddit.com/r/anime/comments/1v2petg/red_river_sora_wa_akai_kawa_no_hotori_episode_3/",
    "seasonYear": 2026,
    "season": "SUMMER"
  },
  {
    "reddit_title": "The Oblivious Saint Can't Contain Her Power • Mujikaku Seijo wa Kyou mo Muishiki ni Chikara wo Tare Nagasu - Episode 4 discussion",
    "matched_anime_id": 196219,
    "matched_anime_native": "無自覚聖女は今日も無意識に力を垂れ流す",
    "score": 100.0,
    "num_comments": 68,
    "url": "https://www.reddit.com/r/anime/comments/1v2imvb/the_oblivious_saint_cant_contain_her_power/",
    "seasonYear": 2026,
    "season": "SUMMER"
  },
  {
    "reddit_title": "Dodgeball Girl Danko • Honoo no Toukyuujo: Dodge Danko - Episode 3 discussion",
    "matched_anime_id": 195833,
    "matched_anime_native": "炎の闘球女 ドッジ弾子",
    "score": 96.7741935483871,
    "num_comments": 7,
    "url": "https://www.reddit.com/r/anime/comments/1v2cxn0/dodgeball_girl_danko_honoo_no_toukyuujo_dodge/",
    "seasonYear": 2026,
    "season": "SUMMER"
  },
  {
    "reddit_title": "Yoroi Shin Den Samurai Troopers Part 2 • Yoroi-Shinden Samurai Troopers Part 2 - Episode 3 discussion",
    "matched_anime_id": 209800,
    "matched_anime_native": "鎧真伝サムライトルーパー 第2クール",
    "score": 100.0,
    "num_comments": 6,
    "url": "https://www.reddit.com/r/anime/comments/1v2l7v6/yoroi_shin_den_samurai_troopers_part_2/",
    "seasonYear": 2026,
    "season": "SUMMER"
  },
  {
    "reddit_title": "Grand Blue Dreaming Season 3 • Grand Blue Season 3 - Episode 3 discussion",
    "matched_anime_id": 199111,
    "matched_anime_native": "ぐらんぶる Season 3",
    "score": 100.0,
    "num_comments": 79,
    "url": "https://www.reddit.com/r/anime/comments/1v1oule/grand_blue_dreaming_season_3_grand_blue_season_3/",
    "seasonYear": 2026,
    "season": "SUMMER"
  },
  {
    "reddit_title": "Liar Game - Episode 16 discussion",
    "matched_anime_id": 197754,
    "matched_anime_native": "LIAR GAME",
    "score": 100.0,
    "num_comments": 99,
    "url": "https://www.reddit.com/r/anime/comments/1v1poru/liar_game_episode_16_discussion/",
    "seasonYear": 2026,
    "season": "SPRING"
  },
  {
    "reddit_title": "Oh Boy, Was I Wrong About Her • Tenkou-saki no Seiso Karen na Bishoujo ga, Mukashi Danshi to Omotte Issho ni Asonda Osananajimi Datta Ken - Episode 3 discussion",
    "matched_anime_id": 169583,
    "matched_anime_native": "転校先の清楚可憐な美少女が、昔男子と思って一緒に遊んだ幼馴染だった件",
    "score": 100.0,
    "num_comments": 92,
    "url": "https://www.reddit.com/r/anime/comments/1v1o23a/oh_boy_was_i_wrong_about_her_tenkousaki_no_seiso/",
    "seasonYear": 2026,
    "season": "SUMMER"
  },
  {
    "reddit_title": "A Livid Lady's Guide to Getting Even: How I Crushed My Homeland with My Mighty Grimoires • Buchigire Reijou wa Houfuku wo Chikaimashita. Madousho no Chikara de Sokoku wo Tatakitsubushimasu - Episode 3 discussion",
    "matched_anime_id": 199408,
    "matched_anime_native": "ブチ切れ令嬢は報復を誓いました。　～魔導書の力で祖国を叩き潰します～",
    "score": 100.0,
    "num_comments": 275,
    "url": "https://www.reddit.com/r/anime/comments/1v1n88p/a_livid_ladys_guide_to_getting_even_how_i_crushed/",
    "seasonYear": 2026,
    "season": "SUMMER"
  },
  {
    "reddit_title": "Skeleton Knight in Another World Season 2 • Gaikotsu Kishi-sama, Tadaima Isekai e Odekakechuu II - Episode 3 discussion",
    "matched_anime_id": 185542,
    "matched_anime_native": "骸骨騎士様、只今異世界へお出掛け中Ⅱ",
    "score": 100.0,
    "num_comments": 101,
    "url": "https://www.reddit.com/r/anime/comments/1v1nl3m/skeleton_knight_in_another_world_season_2/",
    "seasonYear": 2026,
    "season": "SUMMER"
  },
  {
    "reddit_title": "The World Is Dancing • World Is Dancing - Episode 4 discussion",
    "matched_anime_id": 206521,
    "matched_anime_native": "ワールド イズ ダンシング",
    "score": 100.0,
    "num_comments": 52,
    "url": "https://www.reddit.com/r/anime/comments/1v1lr9j/the_world_is_dancing_world_is_dancing_episode_4/",
    "seasonYear": 2026,
    "season": "SUMMER"
  },
  {
    "reddit_title": "Love Unseen Beneath the Clear Night Sky • Toumei na Yoru ni Kakeru Kimi to, Me ni Mienai Koi wo Shita. - Episode 3 discussion",
    "matched_anime_id": 202269,
    "matched_anime_native": "透明な夜に駆ける君と、目に見えない恋をした。",
    "score": 100.0,
    "num_comments": 180,
    "url": "https://www.reddit.com/r/anime/comments/1v1k8f5/love_unseen_beneath_the_clear_night_sky_toumei_na/",
    "seasonYear": 2026,
    "season": "SUMMER"
  },
  {
    "reddit_title": "The Insipid Prince's Furtive Grab for The Throne • Saikyou Degarashi Ouji no Anyaku Teii Arasoi: Munou wo Enjiru SS Rank Ouji wa Koui Keishousen wo Kage kara Shihai suru - Episode 3 discussion",
    "matched_anime_id": 169582,
    "matched_anime_native": "最強出涸らし皇子の暗躍帝位争い 無能を演じるSSランク皇子は皇位継承戦を影から支配する",
    "score": 100.0,
    "num_comments": 73,
    "url": "https://www.reddit.com/r/anime/comments/1v1nk1e/the_insipid_princes_furtive_grab_for_the_throne/",
    "seasonYear": 2026,
    "season": "SUMMER"
  },
  {
    "reddit_title": "The Forsaken Saintess and Her Foodie Road Trip in Another World • Suterare Seijo no Isekai Gohan Tabi: Kakure Skill de Camping Car wo Shoukan shimashita - Episode 3 discussion",
    "matched_anime_id": 209504,
    "matched_anime_native": "捨てられ聖女の異世界ごはん旅 隠れスキルでキャンピングカーを召喚しました",
    "score": 98.80952380952381,
    "num_comments": 34,
    "url": "https://www.reddit.com/r/anime/comments/1v1ncz4/the_forsaken_saintess_and_her_foodie_road_trip_in/",
    "seasonYear": 2026,
    "season": "SUMMER"
  },
  {
    "reddit_title": "That isn't a kiss, it's restoration magic [I Want to Love You Till Your Dying Day]",
    "matched_anime_id": 187260,
    "matched_anime_native": "きみが死ぬまで恋をしたい",
    "score": 100.0,
    "num_comments": 39,
    "url": "https://v.redd.it/zi81rgx09aeh1",
    "seasonYear": 2026,
    "season": "SUMMER"
  },
  {
    "reddit_title": "Mushoku Tensei: Jobless Reincarnation Season 3 • Mushoku Tensei III: Isekai Ittara Honki Dasu - Episode 4 discussion",
    "matched_anime_id": 178789,
    "matched_anime_native": "無職転生Ⅲ ～異世界行ったら本気だす～",
    "score": 100.0,
    "num_comments": 1003,
    "url": "https://www.reddit.com/r/anime/comments/1v0syde/mushoku_tensei_jobless_reincarnation_season_3/",
    "seasonYear": 2026,
    "season": "SUMMER"
  },
  {
    "reddit_title": "\"Saga of Tanya the Evil II\" Web Preview | Episode 3 \"The Well-Intentioned Intermediary\"",
    "matched_anime_id": 135865,
    "matched_anime_native": "幼女戦記Ⅱ",
    "score": 85.18518518518519,
    "num_comments": 1,
    "url": "https://www.youtube.com/watch?v=7nWwC2aD7dI",
    "seasonYear": 2026,
    "season": "SUMMER"
  },
  {
    "reddit_title": "Hokuto no Ken: Kenougun Zako-tachi no Banka • Elegy for the Henchmen: Fist of the North Star - Episode 15 discussion",
    "matched_anime_id": 213506,
    "matched_anime_native": "北斗の拳 拳王軍ザコたちの挽歌 第2クール",
    "score": 92.47311827956989,
    "num_comments": 2,
    "url": "https://www.reddit.com/r/anime/comments/1v1pof7/hokuto_no_ken_kenougun_zakotachi_no_banka_elegy/",
    "seasonYear": 2026,
    "season": "SUMMER"
  },
  {
    "reddit_title": "The 100 Girlfriends Who Really, Really, Really, Really, REALLY Love You Season 3 • Kimi no Koto ga Daidaidaidaidaisuki na 100-nin no Kanojo Season 3 - Episode 3 discussion",
    "matched_anime_id": 200637,
    "matched_anime_native": "君のことが大大大大大好きな100人の彼女 第3期",
    "score": 100.0,
    "num_comments": 395,
    "url": "https://www.reddit.com/r/anime/comments/1v0rzma/the_100_girlfriends_who_really_really_really/",
    "seasonYear": 2026,
    "season": "SUMMER"
  },
  {
    "reddit_title": "Goodbye, Lara • Sayonara Lara - Episode 3 discussion",
    "matched_anime_id": 177637,
    "matched_anime_native": "さよなら ララ",
    "score": 100.0,
    "num_comments": 275,
    "url": "https://www.reddit.com/r/anime/comments/1v0tlkj/goodbye_lara_sayonara_lara_episode_3_discussion/",
    "seasonYear": 2026,
    "season": "SUMMER"
  },
  {
    "reddit_title": "Though I Am an Inept Villainess • Futsutsuka na Akujo dewa Gozaimasu ga: Suuguu Chouso Torikae Den - Episode 2 discussion",
    "matched_anime_id": 188139,
    "matched_anime_native": "ふつつかな悪女ではございますが ~雛宮蝶鼠とりかえ伝~",
    "score": 100.0,
    "num_comments": 224,
    "url": "https://www.reddit.com/r/anime/comments/1v0tz5j/though_i_am_an_inept_villainess_futsutsuka_na/",
    "seasonYear": 2026,
    "season": "SUMMER"
  },
  {
    "reddit_title": "Sparks of Tomorrow • Nijuuseiki Denki Mokuroku -Eureka Evrika- - Episode 3 discussion",
    "matched_anime_id": 103303,
    "matched_anime_native": "二十世紀電氣目録-ユーレカ・エヴリカ-",
    "score": 100.0,
    "num_comments": 200,
    "url": "https://www.reddit.com/r/anime/comments/1v0rt64/sparks_of_tomorrow_nijuuseiki_denki_mokuroku/",
    "seasonYear": 2026,
    "season": "SUMMER"
  },
  {
    "reddit_title": "What learning actually teaches one [ Jaadugar: A Witch in Mongolia ]",
    "matched_anime_id": 190569,
    "matched_anime_native": "天幕のジャードゥーガル",
    "score": 100.0,
    "num_comments": 54,
    "url": "https://v.redd.it/saf0986ro4eh1",
    "seasonYear": 2026,
    "season": "SUMMER"
  },
  {
    "reddit_title": "You and I Are Polar Opposites Season 2 • Seihantai na Kimi to Boku Season 2 - Episode 3 discussion",
    "matched_anime_id": 210031,
    "matched_anime_native": "正反対な君と僕 第2期",
    "score": 100.0,
    "num_comments": 227,
    "url": "https://www.reddit.com/r/anime/comments/1v0l2yx/you_and_i_are_polar_opposites_season_2_seihantai/",
    "seasonYear": 2026,
    "season": "SUMMER"
  },
  {
    "reddit_title": "The Classroom of a Black Cat and a Witch • Kuroneko to Majo no Kyoushitsu - Episode 15 discussion",
    "matched_anime_id": 196974,
    "matched_anime_native": "黒猫と魔女の教室",
    "score": 100.0,
    "num_comments": 60,
    "url": "https://www.reddit.com/r/anime/comments/1v0stug/the_classroom_of_a_black_cat_and_a_witch_kuroneko/",
    "seasonYear": 2026,
    "season": "SPRING"
  },
  {
    "reddit_title": "Though I Am an Inept Villainess (Futsutsuka na Akujo dewa Gozaimasu ga: Suuguu Chouso Torikae Den) Creditless Ending - Houkiboshi by Rokudenashi",
    "matched_anime_id": 188139,
    "matched_anime_native": "ふつつかな悪女ではございますが ~雛宮蝶鼠とりかえ伝~",
    "score": 100.0,
    "num_comments": 6,
    "url": "https://www.youtube.com/watch?v=T3gqwRlME5Q",
    "seasonYear": 2026,
    "season": "SUMMER"
  },
  {
    "reddit_title": "The World's Strongest Rearguard • Sekai Saikyou no Kouei - Episode 3 discussion",
    "matched_anime_id": 198409,
    "matched_anime_native": "世界最強の後衛 ～迷宮国の新人探索者～",
    "score": 100.0,
    "num_comments": 116,
    "url": "https://www.reddit.com/r/anime/comments/1v0q3bn/the_worlds_strongest_rearguard_sekai_saikyou_no/",
    "seasonYear": 2026,
    "season": "SUMMER"
  },
  {
    "reddit_title": "Anime AzurLane: Slow Ahead! Season 2 • Azur Lane: Bisoku Zenshin! Ni!! - Episode 3 discussion",
    "matched_anime_id": 169080,
    "matched_anime_native": "アズールレーン びそくぜんしんっ！にっ！！",
    "score": 100.0,
    "num_comments": 7,
    "url": "https://www.reddit.com/r/anime/comments/1v0vjmr/anime_azurlane_slow_ahead_season_2_azur_lane/",
    "seasonYear": 2026,
    "season": "SUMMER"
  },
  {
    "reddit_title": "Iron Wok Jan! • Tetsunabe no Jan! - Episode 3 discussion",
    "matched_anime_id": 204060,
    "matched_anime_native": "鉄鍋のジャン！",
    "score": 100.0,
    "num_comments": 84,
    "url": "https://www.reddit.com/r/anime/comments/1v0lldk/iron_wok_jan_tetsunabe_no_jan_episode_3_discussion/",
    "seasonYear": 2026,
    "season": "SUMMER"
  },
  {
    "reddit_title": "\"From Overshadowed to Overpowered: Second Reincarnation of a Talentless Sage\" new story arc visual",
    "matched_anime_id": 208044,
    "matched_anime_native": "落第賢者の学院無双～二度目の転生、Sランクチート魔術師冒険録～",
    "score": 100.0,
    "num_comments": 33,
    "url": "https://i.redd.it/o3u2shm9c6eh1.jpeg",
    "seasonYear": 2026,
    "season": "SUMMER"
  },
  {
    "reddit_title": "\"Sayonara, Lara\" (Goodbye, Lara) Creditless Ending | ♪ Ending Theme: Hana Hope – \"Hearts Glow\"",
    "matched_anime_id": 177637,
    "matched_anime_native": "さよなら ララ",
    "score": 100.0,
    "num_comments": 3,
    "url": "https://youtu.be/od3XN58Gnws?si=w0wT0FkJ7FjEUGEI",
    "seasonYear": 2026,
    "season": "SUMMER"
  },
  {
    "reddit_title": "Jaadugar: A Witch in Mongolia | Full Main Visual",
    "matched_anime_id": 190569,
    "matched_anime_native": "天幕のジャードゥーガル",
    "score": 100.0,
    "num_comments": 103,
    "url": "https://anime-jaadugar.com/wp-content/uploads/2026/07/full_EN.jpg",
    "seasonYear": 2026,
    "season": "SUMMER"
  },
  {
    "reddit_title": "Daemons of the Shadow Realm • Yomi no Tsugai - Episode 15 discussion",
    "matched_anime_id": 195600,
    "matched_anime_native": "黄泉のツガイ",
    "score": 100.0,
    "num_comments": 274,
    "url": "https://www.reddit.com/r/anime/comments/1uzzotl/daemons_of_the_shadow_realm_yomi_no_tsugai/",
    "seasonYear": 2026,
    "season": "SPRING"
  },
  {
    "reddit_title": "Let's Go Kaikigumi - Episode 3 discussion",
    "matched_anime_id": 200230,
    "matched_anime_native": "レッツゴー怪奇組",
    "score": 100.0,
    "num_comments": 26,
    "url": "https://www.reddit.com/r/anime/comments/1v0l2zo/lets_go_kaikigumi_episode_3_discussion/",
    "seasonYear": 2026,
    "season": "SUMMER"
  },
  {
    "reddit_title": "Jaadugar: A Witch in Mongolia • Tenmaku no Jaadugar - Episode 4 discussion",
    "matched_anime_id": 190569,
    "matched_anime_native": "天幕のジャードゥーガル",
    "score": 100.0,
    "num_comments": 312,
    "url": "https://www.reddit.com/r/anime/comments/1uzzosb/jaadugar_a_witch_in_mongolia_tenmaku_no_jaadugar/",
    "seasonYear": 2026,
    "season": "SUMMER"
  },
  {
    "reddit_title": "For those of you paying attention to Yutaka Yamada's soundtrack for Black Torch, what are y'all's thoughts?",
    "matched_anime_id": 187538,
    "matched_anime_native": "BLACK TORCH",
    "score": 100.0,
    "num_comments": 4,
    "url": "https://www.reddit.com/r/anime/comments/1v0vs5h/for_those_of_you_paying_attention_to_yutaka/",
    "seasonYear": 2026,
    "season": "SUMMER"
  },
  {
    "reddit_title": "One of the Most Visceral yet Gorgeously Animated Dance Sequence I've ever seen, from an anime that came out of nowhere and still managed to give us a strong contender for \"Best Animated Sequence of the Year\" [The World is Dancing]",
    "matched_anime_id": 206521,
    "matched_anime_native": "ワールド イズ ダンシング",
    "score": 100.0,
    "num_comments": 55,
    "url": "https://v.redd.it/vgqb6uo100eh1",
    "seasonYear": 2026,
    "season": "SUMMER"
  },
  {
    "reddit_title": "Rich Girl Caretaker: I'm Secretly the Caregiver of the Most Popular Girl in This Rich Kid School • Saijo no Osewa: Takane no Hanadarake na Meimonkou de, Gakuin Ichi no Ojousama (Seikatsu Nouryoku Kaimu) wo Kagenagara Osewa suru Koto ni Narimashita - Episode 3 discussion",
    "matched_anime_id": 201514,
    "matched_anime_native": "才女のお世話 高嶺の花だらけな名門校で、学院一のお嬢様(生活能力皆無)を陰ながらお世話することになりました",
    "score": 100.0,
    "num_comments": 141,
    "url": "https://www.reddit.com/r/anime/comments/1v0348r/rich_girl_caretaker_im_secretly_the_caregiver_of/",
    "seasonYear": 2026,
    "season": "SUMMER"
  },
  {
    "reddit_title": "\"Making manga isn't easy. It's even harder if you love it.\" [Draw This, Then Die!]",
    "matched_anime_id": 188525,
    "matched_anime_native": "これ描いて死ね",
    "score": 100.0,
    "num_comments": 4,
    "url": "https://v.redd.it/0pphl1e3q2eh1",
    "seasonYear": 2026,
    "season": "SUMMER"
  },
  {
    "reddit_title": "Hanaori-san Still Wants to Fight in the Next Life • Hanaori-san wa Tensei Shite mo Kenka ga Shitai - Episode 2 discussion",
    "matched_anime_id": 199066,
    "matched_anime_native": "花織さんは転生しても喧嘩がしたい",
    "score": 100.0,
    "num_comments": 87,
    "url": "https://www.reddit.com/r/anime/comments/1v021a1/hanaorisan_still_wants_to_fight_in_the_next_life/",
    "seasonYear": 2026,
    "season": "SUMMER"
  },
  {
    "reddit_title": "Ascendance of a Bookworm: Adopted Daughter of an Archduke • Honzuki no Gekokujou: Shisho ni Naru Tame ni wa Shudan wo Erandeiraremasen - Ryushu no Youjo - Episode 14 discussion",
    "matched_anime_id": 171110,
    "matched_anime_native": "本好きの下剋上 領主の養女",
    "score": 100.0,
    "num_comments": 569,
    "url": "https://www.reddit.com/r/anime/comments/1uzs71l/ascendance_of_a_bookworm_adopted_daughter_of_an/",
    "seasonYear": 2026,
    "season": "SPRING"
  },
  {
    "reddit_title": "Magilumiere Magical Girls Inc. Season 2 • Kabushikigaisha Magi-Lumière Season 2 - Episode 3 discussion",
    "matched_anime_id": 185692,
    "matched_anime_native": "株式会社マジルミエ 第2期",
    "score": 100.0,
    "num_comments": 44,
    "url": "https://www.reddit.com/r/anime/comments/1v021au/magilumiere_magical_girls_inc_season_2/",
    "seasonYear": 2026,
    "season": "SUMMER"
  },
  {
    "reddit_title": "Grow Up Show: Sunflower Circus • Grow Up Show: Himawari no Circus-dan - Episode 3 discussion",
    "matched_anime_id": 196017,
    "matched_anime_native": "グロウアップショウ ～ひまわりのサーカス団～",
    "score": 100.0,
    "num_comments": 77,
    "url": "https://www.reddit.com/r/anime/comments/1uzzoqx/grow_up_show_sunflower_circus_grow_up_show/",
    "seasonYear": 2026,
    "season": "SUMMER"
  },
  {
    "reddit_title": "The Cat and the Dragon • Neko to Ryuu - Episode 4 discussion",
    "matched_anime_id": 186863,
    "matched_anime_native": "猫と竜",
    "score": 100.0,
    "num_comments": 166,
    "url": "https://www.reddit.com/r/anime/comments/1uzw1ob/the_cat_and_the_dragon_neko_to_ryuu_episode_4/",
    "seasonYear": 2026,
    "season": "SUMMER"
  },
  {
    "reddit_title": "Magical Girl Lyrical Nanoha EXCEEDS Gun Blaze Vengeance • Mahou Shoujo Lyrical Nanoha EXCEEDS: Gun Blaze Vengeance - Episode 3 discussion",
    "matched_anime_id": 185875,
    "matched_anime_native": "魔法少女リリカルなのは EXCEEDS Gun Blaze Vengeance",
    "score": 100.0,
    "num_comments": 68,
    "url": "https://www.reddit.com/r/anime/comments/1v0198v/magical_girl_lyrical_nanoha_exceeds_gun_blaze/",
    "seasonYear": 2026,
    "season": "SUMMER"
  },
  {
    "reddit_title": "Mao - Episode 15 discussion",
    "matched_anime_id": 196012,
    "matched_anime_native": "MAO",
    "score": 100.0,
    "num_comments": 10,
    "url": "https://www.reddit.com/r/anime/comments/1v03sc8/mao_episode_15_discussion/",
    "seasonYear": 2026,
    "season": "SPRING"
  },
  {
    "reddit_title": "Welcome to Demon School! Iruma-kun Season 4 • Mairimashita! Iruma-kun Season 4 - Episode 16 discussion",
    "matched_anime_id": 184492,
    "matched_anime_native": "魔入りました！入間くん 第4シリーズ",
    "score": 100.0,
    "num_comments": 79,
    "url": "https://www.reddit.com/r/anime/comments/1uzsd9u/welcome_to_demon_school_irumakun_season_4/",
    "seasonYear": 2026,
    "season": "SPRING"
  },
  {
    "reddit_title": "Mao - Episode 16 discussion",
    "matched_anime_id": 196012,
    "matched_anime_native": "MAO",
    "score": 100.0,
    "num_comments": 15,
    "url": "https://www.reddit.com/r/anime/comments/1v03skq/mao_episode_16_discussion/",
    "seasonYear": 2026,
    "season": "SPRING"
  },
  {
    "reddit_title": "Black Torch - Episode 3 discussion",
    "matched_anime_id": 187538,
    "matched_anime_native": "BLACK TORCH",
    "score": 100.0,
    "num_comments": 208,
    "url": "https://www.reddit.com/r/anime/comments/1uzvdas/black_torch_episode_3_discussion/",
    "seasonYear": 2026,
    "season": "SUMMER"
  },
  {
    "reddit_title": "Babies of Bread • Pan no Akachan - Episode 3 discussion",
    "matched_anime_id": 212308,
    "matched_anime_native": "パンの赤ちゃん",
    "score": 88.23529411764706,
    "num_comments": 0,
    "url": "https://www.reddit.com/r/anime/comments/1v0m7xh/babies_of_bread_pan_no_akachan_episode_3/",
    "seasonYear": 2026,
    "season": "SUMMER"
  },
  {
    "reddit_title": "The Ogre's Bride • Oni no Hanayome - Episode 3 discussion",
    "matched_anime_id": 194219,
    "matched_anime_native": "鬼の花嫁",
    "score": 100.0,
    "num_comments": 192,
    "url": "https://www.reddit.com/r/anime/comments/1v0199w/the_ogres_bride_oni_no_hanayome_episode_3/",
    "seasonYear": 2026,
    "season": "SUMMER"
  },
  {
    "reddit_title": "The Duke's Son Claims He Won't Love Me Yet Showers Me with Adoration • \"Kimi wo Aisuru Ki wa Nai\" to Itta Jiki Koushaku-sama ga Nazeka Dekiai Shitekimasu - Episode 3 discussion",
    "matched_anime_id": 208225,
    "matched_anime_native": "「きみを愛する気はない」と言った次期公爵様がなぜか溺愛してきます",
    "score": 100.0,
    "num_comments": 31,
    "url": "https://www.reddit.com/r/anime/comments/1v01dt2/the_dukes_son_claims_he_wont_love_me_yet_showers/",
    "seasonYear": 2026,
    "season": "SUMMER"
  },
  {
    "reddit_title": "Where can I watch marikas live meter malfunction?",
    "matched_anime_id": 202523,
    "matched_anime_native": "茉莉花ちゃんの好感度はぶっ壊れている",
    "score": 95.08196721311475,
    "num_comments": 3,
    "url": "https://www.reddit.com/r/anime/comments/1v11caw/where_can_i_watch_marikas_live_meter_malfunction/",
    "seasonYear": 2026,
    "season": "SPRING"
  },
  {
    "reddit_title": "Drawing manga sure isn't easy [Draw This, Then Die! - Episode 2]",
    "matched_anime_id": 188525,
    "matched_anime_native": "これ描いて死ね",
    "score": 100.0,
    "num_comments": 11,
    "url": "https://v.redd.it/26kgn60gyydh1",
    "seasonYear": 2026,
    "season": "SUMMER"
  },
  {
    "reddit_title": "Little Shark's Day Out Season 2 • Odekake Kozame Season 2 - Episode 75 discussion",
    "matched_anime_id": 204269,
    "matched_anime_native": "おでかけ子ザメ シーズン2",
    "score": 100.0,
    "num_comments": 2,
    "url": "https://www.reddit.com/r/anime/comments/1v090ou/little_sharks_day_out_season_2_odekake_kozame/",
    "seasonYear": 2026,
    "season": "SPRING"
  },
  {
    "reddit_title": "Tensei Shitara Slime Datta Ken Season 4 • That Time I Got Reincarnated as a Slime Season 4 - Episode 15 discussion",
    "matched_anime_id": 182205,
    "matched_anime_native": "転生したらスライムだった件 第4期",
    "score": 100.0,
    "num_comments": 287,
    "url": "https://www.reddit.com/r/anime/comments/1uz2a8d/tensei_shitara_slime_datta_ken_season_4_that_time/",
    "seasonYear": 2026,
    "season": "SPRING"
  },
  {
    "reddit_title": "Recommendations from Iwamoto-Senpai • Iwamoto-senpai no Suisen - Episode 3 discussion",
    "matched_anime_id": 206249,
    "matched_anime_native": "岩元先輩ノ推薦",
    "score": 100.0,
    "num_comments": 8,
    "url": "https://www.reddit.com/r/anime/comments/1uzwt15/recommendations_from_iwamotosenpai_iwamotosenpai/",
    "seasonYear": 2026,
    "season": "SUMMER"
  },
  {
    "reddit_title": "The Elusive Samurai Season 2 • Nige Jouzu no Wakagimi Season 2 - Episode 1 discussion",
    "matched_anime_id": 182616,
    "matched_anime_native": "逃げ上手の若君 第二期",
    "score": 100.0,
    "num_comments": 102,
    "url": "https://www.reddit.com/r/anime/comments/1uz3yo1/the_elusive_samurai_season_2_nige_jouzu_no/",
    "seasonYear": 2026,
    "season": "SUMMER"
  },
  {
    "reddit_title": "That Time I Got Reincarnated as a Slime",
    "matched_anime_id": 182205,
    "matched_anime_native": "転生したらスライムだった件 第4期",
    "score": 100.0,
    "num_comments": 44,
    "url": "https://www.reddit.com/r/anime/comments/1uzmjzh/that_time_i_got_reincarnated_as_a_slime/",
    "seasonYear": 2026,
    "season": "SPRING"
  },
  {
    "reddit_title": "Draw This, Then Die! • Kore Kaite Shine - Episode 3 discussion",
    "matched_anime_id": 188525,
    "matched_anime_native": "これ描いて死ね",
    "score": 100.0,
    "num_comments": 115,
    "url": "https://www.reddit.com/r/anime/comments/1uz43j4/draw_this_then_die_kore_kaite_shine_episode_3/",
    "seasonYear": 2026,
    "season": "SUMMER"
  },
  {
    "reddit_title": "\"The Elusive Samurai\" Season 2 — is officially listed for 12 Episodes in total",
    "matched_anime_id": 182616,
    "matched_anime_native": "逃げ上手の若君 第二期",
    "score": 100.0,
    "num_comments": 35,
    "url": "https://nigewaka.run/bddvd/07.html",
    "seasonYear": 2026,
    "season": "SUMMER"
  },
  {
    "reddit_title": "HELL MODE: The Hardcore Gamer Dominates in Another World with Garbage Balancing Season 2 • Hell Mode: Yarikomizuki no Gamer wa Hai Settei no Isekai de Musou suru Season 2 - Episode 3 discussion",
    "matched_anime_id": 209983,
    "matched_anime_native": "ヘルモード ～やり込み好きのゲーマーは廃設定の異世界で無双する～ 2nd Season",
    "score": 100.0,
    "num_comments": 123,
    "url": "https://www.reddit.com/r/anime/comments/1uz4t3t/hell_mode_the_hardcore_gamer_dominates_in_another/",
    "seasonYear": 2026,
    "season": "SUMMER"
  },
  {
    "reddit_title": "The Frontier Lord Begins with Zero Subjects • Ryoumin 0-nin Start no Henkyou Ryoushu-sama - Episode 3 discussion",
    "matched_anime_id": 196218,
    "matched_anime_native": "領民0人スタートの辺境領主様",
    "score": 100.0,
    "num_comments": 207,
    "url": "https://www.reddit.com/r/anime/comments/1uyzyme/the_frontier_lord_begins_with_zero_subjects/",
    "seasonYear": 2026,
    "season": "SUMMER"
  },
  {
    "reddit_title": "Mushoku Tensei: Jobless Reincarnation - Season 3 Episode 4 Preview",
    "matched_anime_id": 178789,
    "matched_anime_native": "無職転生Ⅲ ～異世界行ったら本気だす～",
    "score": 100.0,
    "num_comments": 99,
    "url": "https://youtu.be/Q3KRzFz8PRk?si=seTVG8GPDRIejv82",
    "seasonYear": 2026,
    "season": "SUMMER"
  },
  {
    "reddit_title": "I Became a Legend After My 10 Year-Long Last Stand • Koko wa Ore ni Makasete Saki ni Ike to Itte kara 10-nen ga Tattara Densetsu ni Natteita. - Episode 3 discussion",
    "matched_anime_id": 199748,
    "matched_anime_native": "ここは俺に任せて先に行けと言ってから１０年がたったら伝説になっていた。",
    "score": 100.0,
    "num_comments": 140,
    "url": "https://www.reddit.com/r/anime/comments/1uz0mo7/i_became_a_legend_after_my_10_yearlong_last_stand/",
    "seasonYear": 2026,
    "season": "SUMMER"
  },
  {
    "reddit_title": "Pardon the intrusion anime discussion",
    "matched_anime_id": 202985,
    "matched_anime_native": "ただいま、おじゃまされます！",
    "score": 87.27272727272728,
    "num_comments": 6,
    "url": "https://www.reddit.com/r/anime/comments/1v0bvio/pardon_the_intrusion_anime_discussion/",
    "seasonYear": 2026,
    "season": "SPRING"
  },
  {
    "reddit_title": "KAMUI: He's Behind You • Ushiro no Shoumen Kamui-san - Episode 3 discussion",
    "matched_anime_id": 207674,
    "matched_anime_native": "うしろの正面カムイさん",
    "score": 100.0,
    "num_comments": 24,
    "url": "https://www.reddit.com/r/anime/comments/1uz7sgp/kamui_hes_behind_you_ushiro_no_shoumen_kamuisan/",
    "seasonYear": 2026,
    "season": "SUMMER"
  },
  {
    "reddit_title": "\"The Elusive Samurai\" Season 2 – Non-Credit Opening Video (With Lyrics) | Opening Theme: \"Onigoto\" by Kento Nakajima",
    "matched_anime_id": 182616,
    "matched_anime_native": "逃げ上手の若君 第二期",
    "score": 100.0,
    "num_comments": 3,
    "url": "https://youtu.be/Dgj69Vqr120?si=5f_ZAs2x-Q2FwHPZ",
    "seasonYear": 2026,
    "season": "SUMMER"
  },
  {
    "reddit_title": "Please Excuse My Younger Brothers • Uchi no Otouto-domo ga Sumimasen - Episode 3 discussion",
    "matched_anime_id": 203490,
    "matched_anime_native": "うちの弟どもがすみません",
    "score": 100.0,
    "num_comments": 33,
    "url": "https://www.reddit.com/r/anime/comments/1uz4t4j/please_excuse_my_younger_brothers_uchi_no/",
    "seasonYear": 2026,
    "season": "SUMMER"
  },
  {
    "reddit_title": "The Elusive Samurai Season 2 – Non-Credit Ending Video (With Lyrics) | Ending Theme: \"Romantic ga Hoshii Nara\" (\"If You Want Romance\") by Bocchi Boromaru feat. Nao Kosaka, Yoko Shogenji, and Kaho Fujishima (Hinatazaka46)",
    "matched_anime_id": 182616,
    "matched_anime_native": "逃げ上手の若君 第二期",
    "score": 100.0,
    "num_comments": 3,
    "url": "https://youtu.be/2xkn83S68sM?si=L-jls9dVIGKiDCbq",
    "seasonYear": 2026,
    "season": "SUMMER"
  },
  {
    "reddit_title": "The Drops of God • Kami no Shizuku - Episode 15 discussion",
    "matched_anime_id": 202508,
    "matched_anime_native": "神の雫",
    "score": 100.0,
    "num_comments": 9,
    "url": "https://www.reddit.com/r/anime/comments/1uz342j/the_drops_of_god_kami_no_shizuku_episode_15/",
    "seasonYear": 2026,
    "season": "SPRING"
  },
  {
    "reddit_title": "Is \"Welcome to Demon School, Iruma-Kun\" technically an Isekai? What do you think sets this series apart from the others (aspects and in terms of quality)?",
    "matched_anime_id": 184492,
    "matched_anime_native": "魔入りました！入間くん 第4シリーズ",
    "score": 86.41975308641976,
    "num_comments": 38,
    "url": "https://www.reddit.com/r/anime/comments/1v05t1w/is_welcome_to_demon_school_irumakun_technically/",
    "seasonYear": 2026,
    "season": "SPRING"
  },
  {
    "reddit_title": "Rilakkuma - Episode 16 discussion",
    "matched_anime_id": 183231,
    "matched_anime_native": "リラックマ",
    "score": 100.0,
    "num_comments": 2,
    "url": "https://www.reddit.com/r/anime/comments/1uzhsk3/rilakkuma_episode_16_discussion/",
    "seasonYear": 2026,
    "season": "SPRING"
  },
  {
    "reddit_title": "Smoking Behind the Supermarket with You • Super no Ura de Yani Suu Futari - Episode 2 discussion",
    "matched_anime_id": 196187,
    "matched_anime_native": "スーパーの裏でヤニ吸うふたり",
    "score": 100.0,
    "num_comments": 143,
    "url": "https://www.reddit.com/r/anime/comments/1uyago9/smoking_behind_the_supermarket_with_you_super_no/",
    "seasonYear": 2026,
    "season": "SUMMER"
  },
  {
    "reddit_title": "If you liked Apothecary Diaries, you should be watching \"Though I Am an Inept Villainess\"",
    "matched_anime_id": 188139,
    "matched_anime_native": "ふつつかな悪女ではございますが ~雛宮蝶鼠とりかえ伝~",
    "score": 100.0,
    "num_comments": 75,
    "url": "https://www.reddit.com/r/anime/comments/1uyg4op/if_you_liked_apothecary_diaries_you_should_be/",
    "seasonYear": 2026,
    "season": "SUMMER"
  },
  {
    "reddit_title": "I Became a Legend After My 10 Year-Long Last Stand (Koko wa Ore ni Makasete Saki ni Ike to Itte kara 10-nen ga Tattara Densetsu ni Natteita) Opening - Soredemo Donten wo Koete Yuku by sajou no hana",
    "matched_anime_id": 199748,
    "matched_anime_native": "ここは俺に任せて先に行けと言ってから１０年がたったら伝説になっていた。",
    "score": 100.0,
    "num_comments": 1,
    "url": "https://www.youtube.com/watch?v=lMq8obidFDI",
    "seasonYear": 2026,
    "season": "SUMMER"
  },
  {
    "reddit_title": "Chainsmoker Cat • Yani Neko - Episode 3 discussion",
    "matched_anime_id": 207141,
    "matched_anime_native": "ヤニねこ",
    "score": 100.0,
    "num_comments": 426,
    "url": "https://www.reddit.com/r/anime/comments/1uy7cgg/chainsmoker_cat_yani_neko_episode_3_discussion/",
    "seasonYear": 2026,
    "season": "SUMMER"
  },
  {
    "reddit_title": "Yani Catgirls Don't Play Fighting Games [Yani Neko/Chainsmoker Cat]",
    "matched_anime_id": 207141,
    "matched_anime_native": "ヤニねこ",
    "score": 100.0,
    "num_comments": 48,
    "url": "https://v.redd.it/4s9v2cxgamdh1",
    "seasonYear": 2026,
    "season": "SUMMER"
  },
  {
    "reddit_title": "Street Fighter in my yuri anime [Young Ladies Don't Play Fighting Games]",
    "matched_anime_id": 128757,
    "matched_anime_native": "対ありでした。 ～お嬢さまは格闘ゲームなんてしない～",
    "score": 100.0,
    "num_comments": 150,
    "url": "https://v.redd.it/65ep4jriikdh1",
    "seasonYear": 2026,
    "season": "SUMMER"
  },
  {
    "reddit_title": "Kaiju Girl Caramelise • Otome Kaijuu Caraméliser - Episode 3 discussion",
    "matched_anime_id": 204466,
    "matched_anime_native": "乙女怪獣キャラメリゼ",
    "score": 100.0,
    "num_comments": 265,
    "url": "https://www.reddit.com/r/anime/comments/1uy9mhm/kaiju_girl_caramelise_otome_kaijuu_caraméliser/",
    "seasonYear": 2026,
    "season": "SUMMER"
  },
  {
    "reddit_title": "Babies of Bread • Pan no Akachan - Episode 2 discussion",
    "matched_anime_id": 212308,
    "matched_anime_native": "パンの赤ちゃん",
    "score": 88.23529411764706,
    "num_comments": 2,
    "url": "https://www.reddit.com/r/anime/comments/1uz03hx/babies_of_bread_pan_no_akachan_episode_2/",
    "seasonYear": 2026,
    "season": "SUMMER"
  },
  {
    "reddit_title": "Question about Toumei na Yoru ni Kakeru Kimi to, Me ni Mienai Koi wo Shita.",
    "matched_anime_id": 202269,
    "matched_anime_native": "透明な夜に駆ける君と、目に見えない恋をした。",
    "score": 100.0,
    "num_comments": 8,
    "url": "https://www.reddit.com/r/anime/comments/1uzjv8e/question_about_toumei_na_yoru_ni_kakeru_kimi_to/",
    "seasonYear": 2026,
    "season": "SUMMER"
  },
  {
    "reddit_title": "The Exiled Heavy Knight Knows How to Game the System • Tsuihou sareta Tensei Juukishi wa Game Chishiki de Musou suru - Episode 3 discussion",
    "matched_anime_id": 180136,
    "matched_anime_native": "追放された転生重騎士はゲーム知識で無双する",
    "score": 100.0,
    "num_comments": 396,
    "url": "https://www.reddit.com/r/anime/comments/1uyagn5/the_exiled_heavy_knight_knows_how_to_game_the/",
    "seasonYear": 2026,
    "season": "SUMMER"
  },
  {
    "reddit_title": "From Overshadowed to Overpowered: Second Reincarnation of a Talentless Sage • Rakudai Kenja no Gakuin Musou ~Nidome no Tensei, S-Rank Cheat Majutsushi Boukenroku~ - Episode 4 discussion",
    "matched_anime_id": 208044,
    "matched_anime_native": "落第賢者の学院無双～二度目の転生、Sランクチート魔術師冒険録～",
    "score": 100.0,
    "num_comments": 283,
    "url": "https://www.reddit.com/r/anime/comments/1uybiuf/from_overshadowed_to_overpowered_second/",
    "seasonYear": 2026,
    "season": "SUMMER"
  },
  {
    "reddit_title": "The Cat and the Dragon (Neko to Ryuu) Creditless ED - Tadaima no Basho by shallm",
    "matched_anime_id": 186863,
    "matched_anime_native": "猫と竜",
    "score": 100.0,
    "num_comments": 1,
    "url": "https://www.youtube.com/watch?v=CmP5HMtIOEY",
    "seasonYear": 2026,
    "season": "SUMMER"
  },
  {
    "reddit_title": "The opening of the second season of 'You and I Are Polar Opposites' adapts color pages from the manga, so I thought I'd share them with everyone!",
    "matched_anime_id": 210031,
    "matched_anime_native": "正反対な君と僕 第2期",
    "score": 86.8421052631579,
    "num_comments": 21,
    "url": "https://v.redd.it/jivp7e1vtkdh1",
    "seasonYear": 2026,
    "season": "SUMMER"
  },
  {
    "reddit_title": "\"Sora wa Akai Kawa no Hotori\" (Red River) Anime Ending | Ending Theme 'Reunion' by Miisha Shimizu",
    "matched_anime_id": 207809,
    "matched_anime_native": "天は赤い河のほとり",
    "score": 100.0,
    "num_comments": 1,
    "url": "https://youtu.be/z0cYxw8Eifg",
    "seasonYear": 2026,
    "season": "SUMMER"
  },
  {
    "reddit_title": "BanG Dream! YUME∞MITA New Key Visual",
    "matched_anime_id": 198376,
    "matched_anime_native": "バンドリ！ ゆめ∞みた",
    "score": 100.0,
    "num_comments": 51,
    "url": "https://i.redd.it/i0gpe9v3sldh1.jpeg",
    "seasonYear": 2026,
    "season": "SUMMER"
  },
  {
    "reddit_title": "Dara-san of Reiwa • Reiwa no Dara-san - Episode 3 discussion",
    "matched_anime_id": 203880,
    "matched_anime_native": "令和のダラさん",
    "score": 100.0,
    "num_comments": 197,
    "url": "https://www.reddit.com/r/anime/comments/1uy1lo8/darasan_of_reiwa_reiwa_no_darasan_episode_3/",
    "seasonYear": 2026,
    "season": "SUMMER"
  },
  {
    "reddit_title": "BanG Dream! YUME∞MITA - Episode 5 discussion",
    "matched_anime_id": 198376,
    "matched_anime_native": "バンドリ！ ゆめ∞みた",
    "score": 100.0,
    "num_comments": 78,
    "url": "https://www.reddit.com/r/anime/comments/1uy3uw1/bang_dream_yumemita_episode_5_discussion/",
    "seasonYear": 2026,
    "season": "SUMMER"
  },
  {
    "reddit_title": "A military historian's comments on Tanya the Evil, Season 2, Episode 2 (Spoilers)",
    "matched_anime_id": 135865,
    "matched_anime_native": "幼女戦記Ⅱ",
    "score": 87.09677419354838,
    "num_comments": 13,
    "url": "https://www.reddit.com/r/anime/comments/1uy3ki7/a_military_historians_comments_on_tanya_the_evil/",
    "seasonYear": 2026,
    "season": "SUMMER"
  },
  {
    "reddit_title": "Bungo Stray Dogs WAN! Season 2 - Episode 3 discussion",
    "matched_anime_id": 201667,
    "matched_anime_native": "文豪ストレイドッグス わん！２",
    "score": 97.67441860465115,
    "num_comments": 5,
    "url": "https://www.reddit.com/r/anime/comments/1uyikco/bungo_stray_dogs_wan_season_2_episode_3_discussion/",
    "seasonYear": 2026,
    "season": "SUMMER"
  },
  {
    "reddit_title": "What is the song playing at the beginning of Youjo Senki Season 2 Episode 2?",
    "matched_anime_id": 135865,
    "matched_anime_native": "幼女戦記Ⅱ",
    "score": 85.71428571428572,
    "num_comments": 2,
    "url": "https://www.reddit.com/r/anime/comments/1uz11f4/what_is_the_song_playing_at_the_beginning_of/",
    "seasonYear": 2026,
    "season": "SUMMER"
  },
  {
    "reddit_title": "Jaadugar: A Witch in Mongolia episode 4 WEB preview",
    "matched_anime_id": 190569,
    "matched_anime_native": "天幕のジャードゥーガル",
    "score": 100.0,
    "num_comments": 5,
    "url": "https://youtu.be/DKRxW7zPHE4",
    "seasonYear": 2026,
    "season": "SUMMER"
  },
  {
    "reddit_title": "Mebius Dust - Episode 2 discussion",
    "matched_anime_id": 108992,
    "matched_anime_native": "メビウス・ダスト",
    "score": 100.0,
    "num_comments": 28,
    "url": "https://www.reddit.com/r/anime/comments/1uy5dgk/mebius_dust_episode_2_discussion/",
    "seasonYear": 2026,
    "season": "SUMMER"
  },
  {
    "reddit_title": "Saga of Tanya the Evil Season 2 • Youjo Senki II - Episode 2 discussion",
    "matched_anime_id": 135865,
    "matched_anime_native": "幼女戦記Ⅱ",
    "score": 100.0,
    "num_comments": 310,
    "url": "https://www.reddit.com/r/anime/comments/1ux634m/saga_of_tanya_the_evil_season_2_youjo_senki_ii/",
    "seasonYear": 2026,
    "season": "SUMMER"
  },
  {
    "reddit_title": "[Video] Why? RED induction」Special Animation Movie - MYTH & ROID (Youjo Senki: The Saga of Tanya the Evil II OP)",
    "matched_anime_id": 135865,
    "matched_anime_native": "幼女戦記Ⅱ",
    "score": 85.71428571428572,
    "num_comments": 0,
    "url": "https://www.youtube.com/watch?v=9hrlfMldegI",
    "seasonYear": 2026,
    "season": "SUMMER"
  },
  {
    "reddit_title": "Clevatess Season 2 • Clevatess II: Majuu no Ou to Akago to Shikabane no Yuusha Denshou - Episode 2 discussion",
    "matched_anime_id": 198946,
    "matched_anime_native": "クレバテスⅡ-魔獣の王と偽りの勇者伝承-",
    "score": 100.0,
    "num_comments": 341,
    "url": "https://www.reddit.com/r/anime/comments/1ux3wlj/clevatess_season_2_clevatess_ii_majuu_no_ou_to/",
    "seasonYear": 2026,
    "season": "SUMMER"
  },
  {
    "reddit_title": "\"Mebius Dust\" Creditless Opening | ♪ Opening Theme: Leo Ieiri – \"Mebius\"",
    "matched_anime_id": 108992,
    "matched_anime_native": "メビウス・ダスト",
    "score": 100.0,
    "num_comments": 0,
    "url": "https://youtu.be/DZIN7Fx_K48?si=LYt1v5I1OleSkYQ-",
    "seasonYear": 2026,
    "season": "SUMMER"
  },
  {
    "reddit_title": "Tanya the Gentle - The truth behind the [Saga of Tanya the Evil] propaganda!",
    "matched_anime_id": 135865,
    "matched_anime_native": "幼女戦記Ⅱ",
    "score": 80.64516129032258,
    "num_comments": 51,
    "url": "https://v.redd.it/18vs0f3zyedh1",
    "seasonYear": 2026,
    "season": "SUMMER"
  },
  {
    "reddit_title": "\"Mebius Dust\" Creditless Ending | ♪ Ending Theme: Ai Tomioka – \"Dilemma\"",
    "matched_anime_id": 108992,
    "matched_anime_native": "メビウス・ダスト",
    "score": 100.0,
    "num_comments": 0,
    "url": "https://youtu.be/00D8aV_cT6c?si=dZuZwKaWCiD5H0lJ",
    "seasonYear": 2026,
    "season": "SUMMER"
  },
  {
    "reddit_title": "From Old Country Bumpkin to Master Swordsman Season 2 • Katainaka no Ossan, Kensei ni Naru II - Episode 2 discussion",
    "matched_anime_id": 194829,
    "matched_anime_native": "片田舎のおっさん、剣聖になるII",
    "score": 100.0,
    "num_comments": 108,
    "url": "https://www.reddit.com/r/anime/comments/1ux942r/from_old_country_bumpkin_to_master_swordsman/",
    "seasonYear": 2026,
    "season": "SUMMER"
  },
  {
    "reddit_title": "Trapped in a Dating Sim: The World of Otome Games is Tough for Mobs Season 2 • Otome Game Sekai wa Mob ni Kibishii Sekai desu 2 - Episode 2 discussion",
    "matched_anime_id": 159309,
    "matched_anime_native": "乙女ゲー世界はモブに厳しい世界です2",
    "score": 100.0,
    "num_comments": 174,
    "url": "https://www.reddit.com/r/anime/comments/1ux992v/trapped_in_a_dating_sim_the_world_of_otome_games/",
    "seasonYear": 2026,
    "season": "SUMMER"
  },
  {
    "reddit_title": "My Stepmother and Stepsisters Aren’t Wicked • Ibitte Konai Gibo to Gishi - Episode 2 discussion",
    "matched_anime_id": 196356,
    "matched_anime_native": "いびってこない義母と義姉",
    "score": 100.0,
    "num_comments": 50,
    "url": "https://www.reddit.com/r/anime/comments/1uxe134/my_stepmother_and_stepsisters_arent_wicked_ibitte/",
    "seasonYear": 2026,
    "season": "SUMMER"
  },
  {
    "reddit_title": "Heroine? Saint? No, I'm an All-Works Maid (And Proud of It)! • Heroine? Seijo? Iie, All Works Maid desu (Hokori)! - Episode 4 discussion",
    "matched_anime_id": 192800,
    "matched_anime_native": "ヒロイン？聖女？いいえ、オールワークスメイドです（誇）！",
    "score": 100.0,
    "num_comments": 159,
    "url": "https://www.reddit.com/r/anime/comments/1ux7l49/heroine_saint_no_im_an_allworks_maid_and_proud_of/",
    "seasonYear": 2026,
    "season": "SUMMER"
  },
  {
    "reddit_title": "The Villager of Level 999 • Lv999 no Murabito - Episode 4 discussion",
    "matched_anime_id": 197715,
    "matched_anime_native": "LV999の村人",
    "score": 100.0,
    "num_comments": 115,
    "url": "https://www.reddit.com/r/anime/comments/1uxa6t5/the_villager_of_level_999_lv999_no_murabito/",
    "seasonYear": 2026,
    "season": "SUMMER"
  },
  {
    "reddit_title": "Is \"Young Ladies Don’t Play Fighting Games\" actually yuri? Will there be real romantic developments or is it just played for laughs?",
    "matched_anime_id": 128757,
    "matched_anime_native": "対ありでした。 ～お嬢さまは格闘ゲームなんてしない～",
    "score": 100.0,
    "num_comments": 7,
    "url": "https://www.reddit.com/r/anime/comments/1uysbyw/is_young_ladies_dont_play_fighting_games_actually/",
    "seasonYear": 2026,
    "season": "SUMMER"
  },
  {
    "reddit_title": "Mushoku Tensei: Jobless Reincarnation- Season 3 Episode 4 Preview Images",
    "matched_anime_id": 178789,
    "matched_anime_native": "無職転生Ⅲ ～異世界行ったら本気だす～",
    "score": 100.0,
    "num_comments": 50,
    "url": "https://mushokutensei.jp/story/3-04/",
    "seasonYear": 2026,
    "season": "SUMMER"
  },
  {
    "reddit_title": "'Saga of Tanya the Evil II' Non-credit Opening Video | MYTH & ROID — 'Why? RED induction'\"",
    "matched_anime_id": 135865,
    "matched_anime_native": "幼女戦記Ⅱ",
    "score": 85.24590163934427,
    "num_comments": 8,
    "url": "https://youtu.be/IVyvkwvsqW0?si=OLA4g_u1bx8XDwrY",
    "seasonYear": 2026,
    "season": "SUMMER"
  },
  {
    "reddit_title": "You and I Are Polar Opposites (Seihantai na Kimi to Boku) Season 2 Creditless ED - Unmei no Kimi by Mega Shinnosuke",
    "matched_anime_id": 210031,
    "matched_anime_native": "正反対な君と僕 第2期",
    "score": 91.89189189189189,
    "num_comments": 9,
    "url": "https://www.youtube.com/watch?v=FlqDBh8QjZk",
    "seasonYear": 2026,
    "season": "SUMMER"
  },
  {
    "reddit_title": "Hana-Kimi Season 2 • Hanazakari no Kimitachi e Season 2 - Episode 4 discussion",
    "matched_anime_id": 209669,
    "matched_anime_native": "花ざかりの君たちへ 第2期",
    "score": 100.0,
    "num_comments": 31,
    "url": "https://www.reddit.com/r/anime/comments/1uxa6ru/hanakimi_season_2_hanazakari_no_kimitachi_e/",
    "seasonYear": 2026,
    "season": "SUMMER"
  },
  {
    "reddit_title": "Thunder 3 - Episode 2 discussion",
    "matched_anime_id": 207254,
    "matched_anime_native": "サンダー３",
    "score": 100.0,
    "num_comments": 21,
    "url": "https://www.reddit.com/r/anime/comments/1uxe5tu/thunder_3_episode_2_discussion/",
    "seasonYear": 2026,
    "season": "SUMMER"
  },
  {
    "reddit_title": "'Saga of Tanya the Evil II' Non-credit Ending Video | Tanya Degurechaff (CV: Aoi Yuki) — 'Weiter! Weiter!'",
    "matched_anime_id": 135865,
    "matched_anime_native": "幼女戦記Ⅱ",
    "score": 85.24590163934427,
    "num_comments": 4,
    "url": "https://youtu.be/x2k_iYCGKvE?si=prn_ULIKqfq3GbHW",
    "seasonYear": 2026,
    "season": "SUMMER"
  },
  {
    "reddit_title": "\"Chainsmoker Cat\" Episode 3 Preview",
    "matched_anime_id": 207141,
    "matched_anime_native": "ヤニねこ",
    "score": 100.0,
    "num_comments": 26,
    "url": "https://www.youtube.com/watch?v=SA7KnAfiJuY",
    "seasonYear": 2026,
    "season": "SUMMER"
  },
  {
    "reddit_title": "Candy Caries - Episode 14 discussion",
    "matched_anime_id": 205772,
    "matched_anime_native": "キャンディーカリエス",
    "score": 100.0,
    "num_comments": 4,
    "url": "https://www.reddit.com/r/anime/comments/1uxdohr/candy_caries_episode_14_discussion/",
    "seasonYear": 2026,
    "season": "SPRING"
  },
  {
    "reddit_title": "The Ghost in the Shell • Koukaku Kidoutai (TV) - Episode 2 discussion",
    "matched_anime_id": 177699,
    "matched_anime_native": "攻殻機動隊 THE GHOST IN THE SHELL",
    "score": 100.0,
    "num_comments": 393,
    "url": "https://www.reddit.com/r/anime/comments/1uwan6v/the_ghost_in_the_shell_koukaku_kidoutai_tv/",
    "seasonYear": 2026,
    "season": "SUMMER"
  },
  {
    "reddit_title": "\"Grand Blue Dreaming\" Season 3 – Non-Credit Ending | Ending Theme: \"Naked Mermaid\" by Mameshiba no Taigun",
    "matched_anime_id": 199111,
    "matched_anime_native": "ぐらんぶる Season 3",
    "score": 100.0,
    "num_comments": 0,
    "url": "https://youtu.be/c-kKrErfKvM?si=pk18MMLBbrf0pou8",
    "seasonYear": 2026,
    "season": "SUMMER"
  },
  {
    "reddit_title": "I Want to Love You Till Your Dying Day • Kimi ga Shinu made Koi wo Shitai - Episode 2 discussion",
    "matched_anime_id": 187260,
    "matched_anime_native": "きみが死ぬまで恋をしたい",
    "score": 100.0,
    "num_comments": 221,
    "url": "https://www.reddit.com/r/anime/comments/1uw7ezd/i_want_to_love_you_till_your_dying_day_kimi_ga/",
    "seasonYear": 2026,
    "season": "SUMMER"
  },
  {
    "reddit_title": "Every movie reference in the Chainsmoker cat OP side by side",
    "matched_anime_id": 207141,
    "matched_anime_native": "ヤニねこ",
    "score": 100.0,
    "num_comments": 3,
    "url": "https://www.youtube.com/watch?v=rrKD1BRb3NU",
    "seasonYear": 2026,
    "season": "SUMMER"
  },
  {
    "reddit_title": "Young Ladies Don’t Play Fighting Games • Tai-Ari deshita. Ojou-sama wa Kakutou Game Nante Shinai - Episode 2 discussion",
    "matched_anime_id": 128757,
    "matched_anime_native": "対ありでした。 ～お嬢さまは格闘ゲームなんてしない～",
    "score": 100.0,
    "num_comments": 297,
    "url": "https://www.reddit.com/r/anime/comments/1uw629f/young_ladies_dont_play_fighting_games_taiari/",
    "seasonYear": 2026,
    "season": "SUMMER"
  },
  {
    "reddit_title": "Victoria of Many Faces • Tefuda ga Oome no Victoria - Episode 2 discussion",
    "matched_anime_id": 198709,
    "matched_anime_native": "手札が多めのビクトリア",
    "score": 100.0,
    "num_comments": 153,
    "url": "https://www.reddit.com/r/anime/comments/1uwb6rl/victoria_of_many_faces_tefuda_ga_oome_no_victoria/",
    "seasonYear": 2026,
    "season": "SUMMER"
  },
  {
    "reddit_title": "Agents of the Four Seasons",
    "matched_anime_id": 190143,
    "matched_anime_native": "春夏秋冬代行者 春の舞",
    "score": 100.0,
    "num_comments": 0,
    "url": "https://youtu.be/iIEMV035qBo",
    "seasonYear": 2026,
    "season": "SPRING"
  },
  {
    "reddit_title": "Red River • Sora wa Akai Kawa no Hotori - Episode 2 discussion",
    "matched_anime_id": 207809,
    "matched_anime_native": "天は赤い河のほとり",
    "score": 100.0,
    "num_comments": 181,
    "url": "https://www.reddit.com/r/anime/comments/1uwfsaa/red_river_sora_wa_akai_kawa_no_hotori_episode_2/",
    "seasonYear": 2026,
    "season": "SUMMER"
  },
  {
    "reddit_title": "I Want to Love You Till Your Dying Day • Opening • Amore by Reona",
    "matched_anime_id": 187260,
    "matched_anime_native": "きみが死ぬまで恋をしたい",
    "score": 100.0,
    "num_comments": 1,
    "url": "https://youtu.be/01Vgu7BIxmI",
    "seasonYear": 2026,
    "season": "SUMMER"
  },
  {
    "reddit_title": "\"Young Ladies Don't Play Fighting Games\" Creditless Ending ♪ | Ending Theme: halca – \"NEW GAME\"",
    "matched_anime_id": 128757,
    "matched_anime_native": "対ありでした。 ～お嬢さまは格闘ゲームなんてしない～",
    "score": 100.0,
    "num_comments": 16,
    "url": "https://youtu.be/GKtdRThIuuE?si=hORzq-b1kSurSOZh",
    "seasonYear": 2026,
    "season": "SUMMER"
  },
  {
    "reddit_title": "The Oblivious Saint Can't Contain Her Power • Mujikaku Seijo wa Kyou mo Muishiki ni Chikara wo Tare Nagasu - Episode 3 discussion",
    "matched_anime_id": 196219,
    "matched_anime_native": "無自覚聖女は今日も無意識に力を垂れ流す",
    "score": 100.0,
    "num_comments": 153,
    "url": "https://www.reddit.com/r/anime/comments/1uw8wdu/the_oblivious_saint_cant_contain_her_power/",
    "seasonYear": 2026,
    "season": "SUMMER"
  },
  {
    "reddit_title": "I Want to Love You Till Your Dying Day • Ending • Eternal by sajou no hana",
    "matched_anime_id": 187260,
    "matched_anime_native": "きみが死ぬまで恋をしたい",
    "score": 100.0,
    "num_comments": 5,
    "url": "https://youtu.be/bszg61aM_7E",
    "seasonYear": 2026,
    "season": "SUMMER"
  },
  {
    "reddit_title": "\"Victoria of Many Faces\" Ending Movie | Ending Theme \"The End of Our Bond\" by KI_EN",
    "matched_anime_id": 198709,
    "matched_anime_native": "手札が多めのビクトリア",
    "score": 100.0,
    "num_comments": 0,
    "url": "https://youtu.be/r6pUQw5xjoc?si=L1f3gXw0z0fzbsSL",
    "seasonYear": 2026,
    "season": "SUMMER"
  },
  {
    "reddit_title": "Little Shark's Day Out Season 2 • Odekake Kozame Season 2 - Episode 74 discussion",
    "matched_anime_id": 204269,
    "matched_anime_native": "おでかけ子ザメ シーズン2",
    "score": 100.0,
    "num_comments": 2,
    "url": "https://www.reddit.com/r/anime/comments/1uwm429/little_sharks_day_out_season_2_odekake_kozame/",
    "seasonYear": 2026,
    "season": "SPRING"
  },
  {
    "reddit_title": "Yoroi Shin Den Samurai Troopers Part 2 • Yoroi-Shinden Samurai Troopers Part 2 - Episode 2 discussion",
    "matched_anime_id": 209800,
    "matched_anime_native": "鎧真伝サムライトルーパー 第2クール",
    "score": 100.0,
    "num_comments": 9,
    "url": "https://www.reddit.com/r/anime/comments/1uwbbqz/yoroi_shin_den_samurai_troopers_part_2/",
    "seasonYear": 2026,
    "season": "SUMMER"
  },
  {
    "reddit_title": "Dodgeball Girl Danko • Honoo no Toukyuujo: Dodge Danko - Episode 2 discussion",
    "matched_anime_id": 195833,
    "matched_anime_native": "炎の闘球女 ドッジ弾子",
    "score": 96.7741935483871,
    "num_comments": 18,
    "url": "https://www.reddit.com/r/anime/comments/1uw2l6b/dodgeball_girl_danko_honoo_no_toukyuujo_dodge/",
    "seasonYear": 2026,
    "season": "SUMMER"
  },
  {
    "reddit_title": "Grand Blue Dreaming Season 3 • Grand Blue Season 3 - Episode 2 discussion",
    "matched_anime_id": 199111,
    "matched_anime_native": "ぐらんぶる Season 3",
    "score": 100.0,
    "num_comments": 124,
    "url": "https://www.reddit.com/r/anime/comments/1uvew0b/grand_blue_dreaming_season_3_grand_blue_season_3/",
    "seasonYear": 2026,
    "season": "SUMMER"
  },
  {
    "reddit_title": "Ghost in the Shell (2026) episode 1 plot confusion",
    "matched_anime_id": 177699,
    "matched_anime_native": "攻殻機動隊 THE GHOST IN THE SHELL",
    "score": 90.0,
    "num_comments": 21,
    "url": "https://www.reddit.com/r/anime/comments/1uw0e91/ghost_in_the_shell_2026_episode_1_plot_confusion/",
    "seasonYear": 2026,
    "season": "SUMMER"
  },
  {
    "reddit_title": "The Insipid Prince's Furtive Grab for The Throne • Saikyou Degarashi Ouji no Anyaku Teii Arasoi: Munou wo Enjiru SS Rank Ouji wa Koui Keishousen wo Kage kara Shihai suru - Episode 2 discussion",
    "matched_anime_id": 169582,
    "matched_anime_native": "最強出涸らし皇子の暗躍帝位争い 無能を演じるSSランク皇子は皇位継承戦を影から支配する",
    "score": 100.0,
    "num_comments": 63,
    "url": "https://www.reddit.com/r/anime/comments/1uvrqns/the_insipid_princes_furtive_grab_for_the_throne/",
    "seasonYear": 2026,
    "season": "SUMMER"
  },
  {
    "reddit_title": "Petitcure ~Precure Fairies~ movie theater etiquette video",
    "matched_anime_id": 209541,
    "matched_anime_native": "ぷちきゅあ～Precure Fairies～ シーズン3",
    "score": 87.09677419354838,
    "num_comments": 0,
    "url": "https://www.youtube.com/watch?v=ODZT6GDLqAw",
    "seasonYear": 2026,
    "season": "SPRING"
  },
  {
    "reddit_title": "Liar Game - Episode 15 discussion",
    "matched_anime_id": 197754,
    "matched_anime_native": "LIAR GAME",
    "score": 100.0,
    "num_comments": 165,
    "url": "https://www.reddit.com/r/anime/comments/1uvfq95/liar_game_episode_15_discussion/",
    "seasonYear": 2026,
    "season": "SPRING"
  },
  {
    "reddit_title": "Skeleton Knight in Another World Season 2 • Gaikotsu Kishi-sama, Tadaima Isekai e Odekakechuu II - Episode 2 discussion",
    "matched_anime_id": 185542,
    "matched_anime_native": "骸骨騎士様、只今異世界へお出掛け中Ⅱ",
    "score": 100.0,
    "num_comments": 131,
    "url": "https://www.reddit.com/r/anime/comments/1uvdzhq/skeleton_knight_in_another_world_season_2/",
    "seasonYear": 2026,
    "season": "SUMMER"
  },
  {
    "reddit_title": "Oh Boy, Was I Wrong About Her • Tenkou-saki no Seiso Karen na Bishoujo ga, Mukashi Danshi to Omotte Issho ni Asonda Osananajimi Datta Ken - Episode 2 discussion",
    "matched_anime_id": 169583,
    "matched_anime_native": "転校先の清楚可憐な美少女が、昔男子と思って一緒に遊んだ幼馴染だった件",
    "score": 100.0,
    "num_comments": 112,
    "url": "https://www.reddit.com/r/anime/comments/1uve2rm/oh_boy_was_i_wrong_about_her_tenkousaki_no_seiso/",
    "seasonYear": 2026,
    "season": "SUMMER"
  },
  {
    "reddit_title": "A Livid Lady's Guide to Getting Even: How I Crushed My Homeland with My Mighty Grimoires • Buchigire Reijou wa Houfuku wo Chikaimashita. Madousho no Chikara de Sokoku wo Tatakitsubushimasu - Episode 2 discussion",
    "matched_anime_id": 199408,
    "matched_anime_native": "ブチ切れ令嬢は報復を誓いました。　～魔導書の力で祖国を叩き潰します～",
    "score": 100.0,
    "num_comments": 329,
    "url": "https://www.reddit.com/r/anime/comments/1uvd8ht/a_livid_ladys_guide_to_getting_even_how_i_crushed/",
    "seasonYear": 2026,
    "season": "SUMMER"
  },
  {
    "reddit_title": "Beautiful Jaadugar: Witch in Mongolia Fanart",
    "matched_anime_id": 190569,
    "matched_anime_native": "天幕のジャードゥーガル",
    "score": 92.85714285714286,
    "num_comments": 1,
    "url": "https://www.reddit.com/r/anime/comments/1uw6x7d/beautiful_jaadugar_witch_in_mongolia_fanart/",
    "seasonYear": 2026,
    "season": "SUMMER"
  },
  {
    "reddit_title": "Love Unseen Beneath the Clear Night Sky • Toumei na Yoru ni Kakeru Kimi to, Me ni Mienai Koi wo Shita. - Episode 2 discussion",
    "matched_anime_id": 202269,
    "matched_anime_native": "透明な夜に駆ける君と、目に見えない恋をした。",
    "score": 100.0,
    "num_comments": 196,
    "url": "https://www.reddit.com/r/anime/comments/1uvab02/love_unseen_beneath_the_clear_night_sky_toumei_na/",
    "seasonYear": 2026,
    "season": "SUMMER"
  },
  {
    "reddit_title": "The World Is Dancing • World Is Dancing - Episode 3 discussion",
    "matched_anime_id": 206521,
    "matched_anime_native": "ワールド イズ ダンシング",
    "score": 100.0,
    "num_comments": 48,
    "url": "https://www.reddit.com/r/anime/comments/1uvbrt5/the_world_is_dancing_world_is_dancing_episode_3/",
    "seasonYear": 2026,
    "season": "SUMMER"
  },
  {
    "reddit_title": "Ghost in The Shell 2026 - Western Animation Style?",
    "matched_anime_id": 177699,
    "matched_anime_native": "攻殻機動隊 THE GHOST IN THE SHELL",
    "score": 90.0,
    "num_comments": 21,
    "url": "https://www.reddit.com/r/anime/comments/1ux6waw/ghost_in_the_shell_2026_western_animation_style/",
    "seasonYear": 2026,
    "season": "SUMMER"
  },
  {
    "reddit_title": "The Forsaken Saintess and Her Foodie Road Trip in Another World • Suterare Seijo no Isekai Gohan Tabi: Kakure Skill de Camping Car wo Shoukan shimashita - Episode 2 discussion",
    "matched_anime_id": 209504,
    "matched_anime_native": "捨てられ聖女の異世界ごはん旅 隠れスキルでキャンピングカーを召喚しました",
    "score": 98.80952380952381,
    "num_comments": 50,
    "url": "https://www.reddit.com/r/anime/comments/1uvdd7p/the_forsaken_saintess_and_her_foodie_road_trip_in/",
    "seasonYear": 2026,
    "season": "SUMMER"
  },
  {
    "reddit_title": "\"My Stepmother and Stepsisters Aren't Wicked\" Non-Credit Opening Movie | Lia \"Amayadori no Shoukei\"",
    "matched_anime_id": 196356,
    "matched_anime_native": "いびってこない義母と義姉",
    "score": 100.0,
    "num_comments": 3,
    "url": "https://www.youtube.com/watch?v=k2Gfd254sMg",
    "seasonYear": 2026,
    "season": "SUMMER"
  },
  {
    "reddit_title": "\"Saga of Tanya the Evil II\" Web Preview | Episode 2 \"A Strange Friendship\"",
    "matched_anime_id": 135865,
    "matched_anime_native": "幼女戦記Ⅱ",
    "score": 85.18518518518519,
    "num_comments": 9,
    "url": "https://www.youtube.com/watch?v=5dqw4E8HDhQ",
    "seasonYear": 2026,
    "season": "SUMMER"
  },
  {
    "reddit_title": "Mushoku Tensei: Jobless Reincarnation Season 3 • Mushoku Tensei III: Isekai Ittara Honki Dasu - Episode 3 discussion",
    "matched_anime_id": 178789,
    "matched_anime_native": "無職転生Ⅲ ～異世界行ったら本気だす～",
    "score": 100.0,
    "num_comments": 1480,
    "url": "https://www.reddit.com/r/anime/comments/1uuhuyx/mushoku_tensei_jobless_reincarnation_season_3/",
    "seasonYear": 2026,
    "season": "SUMMER"
  },
  {
    "reddit_title": "\"Iron Wok Jan!\" – Non-Credit Opening Video",
    "matched_anime_id": 204060,
    "matched_anime_native": "鉄鍋のジャン！",
    "score": 100.0,
    "num_comments": 5,
    "url": "https://youtu.be/wTQdf37-OBk?si=UcIrVy9n7bGqV2Ww",
    "seasonYear": 2026,
    "season": "SUMMER"
  },
  {
    "reddit_title": "The 100 Girlfriends Who Really, Really, Really, Really, REALLY Love You Season 3 • Kimi no Koto ga Daidaidaidaidaisuki na 100-nin no Kanojo Season 3 - Episode 2 discussion",
    "matched_anime_id": 200637,
    "matched_anime_native": "君のことが大大大大大好きな100人の彼女 第3期",
    "score": 100.0,
    "num_comments": 347,
    "url": "https://www.reddit.com/r/anime/comments/1uuh51m/the_100_girlfriends_who_really_really_really/",
    "seasonYear": 2026,
    "season": "SUMMER"
  },
  {
    "reddit_title": "\"I Became a Legend After My 10 Year-Long Last Stand\" Ending Movie | Ending Theme \"Lucky in the Ordinary\" by MEISHOHIKOKAI",
    "matched_anime_id": 199748,
    "matched_anime_native": "ここは俺に任せて先に行けと言ってから１０年がたったら伝説になっていた。",
    "score": 100.0,
    "num_comments": 7,
    "url": "https://youtu.be/UDD-U-c-m9Y?si=A1fdZzWb_yHSl2uB",
    "seasonYear": 2026,
    "season": "SUMMER"
  },
  {
    "reddit_title": "\"Mushoku Tensei III: Jobless Reincarnation\" Non-Credit Ending Video / Ending Theme: \"Inori, Owareba\" by Mika Nakashima",
    "matched_anime_id": 178789,
    "matched_anime_native": "無職転生Ⅲ ～異世界行ったら本気だす～",
    "score": 88.88888888888889,
    "num_comments": 55,
    "url": "https://youtu.be/UKcJqQqiXq0?si=-8n3uHDqOECTyn87",
    "seasonYear": 2026,
    "season": "SUMMER"
  },
  {
    "reddit_title": "「Seihantai na Kimi to Boku」Episode 15 Preview",
    "matched_anime_id": 210031,
    "matched_anime_native": "正反対な君と僕 第2期",
    "score": 86.56716417910448,
    "num_comments": 0,
    "url": "https://www.youtube.com/watch?v=L-c78F1f3nU",
    "seasonYear": 2026,
    "season": "SUMMER"
  },
  {
    "reddit_title": "Goodbye, Lara • Sayonara Lara - Episode 2 discussion",
    "matched_anime_id": 177637,
    "matched_anime_native": "さよなら ララ",
    "score": 100.0,
    "num_comments": 265,
    "url": "https://www.reddit.com/r/anime/comments/1uuio3r/goodbye_lara_sayonara_lara_episode_2_discussion/",
    "seasonYear": 2026,
    "season": "SUMMER"
  },
  {
    "reddit_title": "Though I Am an Inept Villainess • Futsutsuka na Akujo dewa Gozaimasu ga: Suuguu Chouso Torikae Den - Episode 1 discussion",
    "matched_anime_id": 188139,
    "matched_anime_native": "ふつつかな悪女ではございますが ~雛宮蝶鼠とりかえ伝~",
    "score": 100.0,
    "num_comments": 324,
    "url": "https://www.reddit.com/r/anime/comments/1uuh6xl/though_i_am_an_inept_villainess_futsutsuka_na/",
    "seasonYear": 2026,
    "season": "SUMMER"
  },
  {
    "reddit_title": "Sparks of Tomorrow • Nijuuseiki Denki Mokuroku -Eureka Evrika- - Episode 2 discussion",
    "matched_anime_id": 103303,
    "matched_anime_native": "二十世紀電氣目録-ユーレカ・エヴリカ-",
    "score": 100.0,
    "num_comments": 217,
    "url": "https://www.reddit.com/r/anime/comments/1uuguxt/sparks_of_tomorrow_nijuuseiki_denki_mokuroku/",
    "seasonYear": 2026,
    "season": "SUMMER"
  },
  {
    "reddit_title": "TV Anime \"The World Is Dancing\" Creditless Ending | ♪ Ending Theme: hockrockb – \"Nameless Flower\" (TOY'S FACTORY)",
    "matched_anime_id": 206521,
    "matched_anime_native": "ワールド イズ ダンシング",
    "score": 100.0,
    "num_comments": 0,
    "url": "https://youtu.be/kBP_Urtwx7Q?si=kE4RvZPPJotFQWnM",
    "seasonYear": 2026,
    "season": "SUMMER"
  },
  {
    "reddit_title": "You and I Are Polar Opposites Season 2 • Seihantai na Kimi to Boku Season 2 - Episode 2 discussion",
    "matched_anime_id": 210031,
    "matched_anime_native": "正反対な君と僕 第2期",
    "score": 100.0,
    "num_comments": 304,
    "url": "https://www.reddit.com/r/anime/comments/1uu9s0i/you_and_i_are_polar_opposites_season_2_seihantai/",
    "seasonYear": 2026,
    "season": "SUMMER"
  },
  {
    "reddit_title": "Hokuto no Ken: Kenougun Zako-tachi no Banka • Elegy for the Henchmen: Fist of the North Star - Episode 14 discussion",
    "matched_anime_id": 213506,
    "matched_anime_native": "北斗の拳 拳王軍ザコたちの挽歌 第2クール",
    "score": 92.47311827956989,
    "num_comments": 3,
    "url": "https://www.reddit.com/r/anime/comments/1uv9t6e/hokuto_no_ken_kenougun_zakotachi_no_banka_elegy/",
    "seasonYear": 2026,
    "season": "SUMMER"
  },
  {
    "reddit_title": "Goodbye, Lara | Opening by Ikimonogakari",
    "matched_anime_id": 177637,
    "matched_anime_native": "さよなら ララ",
    "score": 100.0,
    "num_comments": 18,
    "url": "https://youtube.com/watch?v=GOfC_4qCa9c",
    "seasonYear": 2026,
    "season": "SUMMER"
  },
  {
    "reddit_title": "Some animation cuts in the OP of 'Goodbye Lara' are made utilising analog cel animation. A making-of video tracking the process planned for release soon. Image sneak peek in the source link.",
    "matched_anime_id": 177637,
    "matched_anime_native": "さよなら ララ",
    "score": 100.0,
    "num_comments": 15,
    "url": "https://x.com/Goodbye_Lara/status/2076337829341471157",
    "seasonYear": 2026,
    "season": "SUMMER"
  },
  {
    "reddit_title": "Short & Sweet | Botan Kamiina Fully Blossoms On a Mountain",
    "matched_anime_id": 187869,
    "matched_anime_native": "上伊那ぼたん、酔へる姿は百合の花",
    "score": 84.61538461538461,
    "num_comments": 10,
    "url": "https://v.redd.it/tyzh4h8i1tch1",
    "seasonYear": 2026,
    "season": "SPRING"
  },
  {
    "reddit_title": "The Classroom of a Black Cat and a Witch • Kuroneko to Majo no Kyoushitsu - Episode 14 discussion",
    "matched_anime_id": 196974,
    "matched_anime_native": "黒猫と魔女の教室",
    "score": 100.0,
    "num_comments": 51,
    "url": "https://www.reddit.com/r/anime/comments/1uuhv01/the_classroom_of_a_black_cat_and_a_witch_kuroneko/",
    "seasonYear": 2026,
    "season": "SPRING"
  },
  {
    "reddit_title": "The World's Strongest Rearguard • Sekai Saikyou no Kouei - Episode 2 discussion",
    "matched_anime_id": 198409,
    "matched_anime_native": "世界最強の後衛 ～迷宮国の新人探索者～",
    "score": 100.0,
    "num_comments": 147,
    "url": "https://www.reddit.com/r/anime/comments/1uueyef/the_worlds_strongest_rearguard_sekai_saikyou_no/",
    "seasonYear": 2026,
    "season": "SUMMER"
  },
  {
    "reddit_title": "Clevatess Season 2 - EP2 WEB Preview",
    "matched_anime_id": 198946,
    "matched_anime_native": "クレバテスⅡ-魔獣の王と偽りの勇者伝承-",
    "score": 100.0,
    "num_comments": 1,
    "url": "https://youtu.be/-TLmxcxZM80?si=j2VH3FPzCLdzHKLm",
    "seasonYear": 2026,
    "season": "SUMMER"
  },
  {
    "reddit_title": "\"Though I Am an Inept Villainess\" is officially listed with 11 episodes in total",
    "matched_anime_id": 188139,
    "matched_anime_native": "ふつつかな悪女ではございますが ~雛宮蝶鼠とりかえ伝~",
    "score": 100.0,
    "num_comments": 5,
    "url": "https://futsutsuka.net/blu-ray/vol2.html",
    "seasonYear": 2026,
    "season": "SUMMER"
  },
  {
    "reddit_title": "\"Sparks of Tomorrow\" Non-Credit Ending | Ending Theme 'Soarin’' by Ginger Root",
    "matched_anime_id": 103303,
    "matched_anime_native": "二十世紀電氣目録-ユーレカ・エヴリカ-",
    "score": 100.0,
    "num_comments": 6,
    "url": "https://youtu.be/lJ6dDUwWOis?si=zFu_RNLU2LARwRLn",
    "seasonYear": 2026,
    "season": "SUMMER"
  },
  {
    "reddit_title": "\"Though I Am an Inept Villainess\" (Futsutsuka na Akujo de wa Gozaimasu ga) Non-Credit Opening | Opening Theme 'Sunny' by milet",
    "matched_anime_id": 188139,
    "matched_anime_native": "ふつつかな悪女ではございますが ~雛宮蝶鼠とりかえ伝~",
    "score": 100.0,
    "num_comments": 2,
    "url": "https://youtu.be/LshSTzPWdLk?si=yBALd-WbJK_6Xgit",
    "seasonYear": 2026,
    "season": "SUMMER"
  },
  {
    "reddit_title": "Anime AzurLane: Slow Ahead! Season 2 • Azur Lane: Bisoku Zenshin! Ni!! - Episode 2 discussion",
    "matched_anime_id": 169080,
    "matched_anime_native": "アズールレーン びそくぜんしんっ！にっ！！",
    "score": 100.0,
    "num_comments": 10,
    "url": "https://www.reddit.com/r/anime/comments/1uukps3/anime_azurlane_slow_ahead_season_2_azur_lane/",
    "seasonYear": 2026,
    "season": "SUMMER"
  },
  {
    "reddit_title": "Rat problem From Old Country Bumpkin to Master Swordsman)",
    "matched_anime_id": 194829,
    "matched_anime_native": "片田舎のおっさん、剣聖になるII",
    "score": 96.7032967032967,
    "num_comments": 25,
    "url": "https://v.redd.it/exwmhlgq8rch1",
    "seasonYear": 2026,
    "season": "SUMMER"
  },
  {
    "reddit_title": "Iron Wok Jan! • Tetsunabe no Jan! - Episode 2 discussion",
    "matched_anime_id": 204060,
    "matched_anime_native": "鉄鍋のジャン！",
    "score": 100.0,
    "num_comments": 83,
    "url": "https://www.reddit.com/r/anime/comments/1uuaas8/iron_wok_jan_tetsunabe_no_jan_episode_2_discussion/",
    "seasonYear": 2026,
    "season": "SUMMER"
  },
  {
    "reddit_title": "Let's Go Kaikigumi - Episode 2 discussion",
    "matched_anime_id": 200230,
    "matched_anime_native": "レッツゴー怪奇組",
    "score": 100.0,
    "num_comments": 40,
    "url": "https://www.reddit.com/r/anime/comments/1uufr50/lets_go_kaikigumi_episode_2_discussion/",
    "seasonYear": 2026,
    "season": "SUMMER"
  },
  {
    "reddit_title": "\"Sparks of Tomorrow\" Creditless Opening | Opening Theme 'Eureka Evrika' by Luna Goami",
    "matched_anime_id": 103303,
    "matched_anime_native": "二十世紀電氣目録-ユーレカ・エヴリカ-",
    "score": 100.0,
    "num_comments": 0,
    "url": "https://x.com/i/status/2076313631000567837",
    "seasonYear": 2026,
    "season": "SUMMER"
  },
  {
    "reddit_title": "Jaadugar: A Witch in Mongolia • Tenmaku no Jaadugar - Episode 3 discussion",
    "matched_anime_id": 190569,
    "matched_anime_native": "天幕のジャードゥーガル",
    "score": 100.0,
    "num_comments": 324,
    "url": "https://www.reddit.com/r/anime/comments/1uto00z/jaadugar_a_witch_in_mongolia_tenmaku_no_jaadugar/",
    "seasonYear": 2026,
    "season": "SUMMER"
  },
  {
    "reddit_title": "\"Hanaori-san Still Wants to Fight in the Next Life\" Creditless Ending ♪ Ending Theme: Maaya Uchida – \"Very Good Encounter\"",
    "matched_anime_id": 199066,
    "matched_anime_native": "花織さんは転生しても喧嘩がしたい",
    "score": 100.0,
    "num_comments": 1,
    "url": "https://youtu.be/mGmKY-PB82o?si=RmBh_RudA9DZlCMG",
    "seasonYear": 2026,
    "season": "SUMMER"
  },
  {
    "reddit_title": "Daemons of the Shadow Realm • Yomi no Tsugai - Episode 14 discussion",
    "matched_anime_id": 195600,
    "matched_anime_native": "黄泉のツガイ",
    "score": 100.0,
    "num_comments": 256,
    "url": "https://www.reddit.com/r/anime/comments/1utmghq/daemons_of_the_shadow_realm_yomi_no_tsugai/",
    "seasonYear": 2026,
    "season": "SPRING"
  },
  {
    "reddit_title": "Anime recs with MCs that actually kill other people",
    "matched_anime_id": 198113,
    "matched_anime_native": "キルアオ",
    "score": 85.71428571428572,
    "num_comments": 84,
    "url": "https://www.reddit.com/r/anime/comments/1uvjjgw/anime_recs_with_mcs_that_actually_kill_other/",
    "seasonYear": 2026,
    "season": "SPRING"
  },
  {
    "reddit_title": "\"Hanaori-san Still Wants to Fight in the Next Life\" Creditless Opening ♪ Opening Theme: Masayoshi Oishi – \"High Maintenance Girl\"",
    "matched_anime_id": 199066,
    "matched_anime_native": "花織さんは転生しても喧嘩がしたい",
    "score": 100.0,
    "num_comments": 3,
    "url": "https://youtu.be/dv1TGoV_aS8?si=6MG57pF4ItDcuAH_",
    "seasonYear": 2026,
    "season": "SUMMER"
  },
  {
    "reddit_title": "Me selling you on \"Though I Am an Inept Villianess\" for 11 minutes",
    "matched_anime_id": 188139,
    "matched_anime_native": "ふつつかな悪女ではございますが ~雛宮蝶鼠とりかえ伝~",
    "score": 96.7741935483871,
    "num_comments": 0,
    "url": "https://youtu.be/vZ2ovalOIjE?si=MS2eQwJfk3QcHGWI",
    "seasonYear": 2026,
    "season": "SUMMER"
  },
  {
    "reddit_title": "Rich Girl Caretaker: I'm Secretly the Caregiver of the Most Popular Girl in This Rich Kid School • Saijo no Osewa: Takane no Hanadarake na Meimonkou de, Gakuin Ichi no Ojousama (Seikatsu Nouryoku Kaimu) wo Kagenagara Osewa suru Koto ni Narimashita - Episode 2 discussion",
    "matched_anime_id": 201514,
    "matched_anime_native": "才女のお世話 高嶺の花だらけな名門校で、学院一のお嬢様(生活能力皆無)を陰ながらお世話することになりました",
    "score": 100.0,
    "num_comments": 166,
    "url": "https://www.reddit.com/r/anime/comments/1utt182/rich_girl_caretaker_im_secretly_the_caregiver_of/",
    "seasonYear": 2026,
    "season": "SUMMER"
  },
  {
    "reddit_title": "\"Draw This, Then Die!\" Creditless Ending ♪ Ending Theme: Regal Lily – \"Conifer\"",
    "matched_anime_id": 188525,
    "matched_anime_native": "これ描いて死ね",
    "score": 100.0,
    "num_comments": 0,
    "url": "https://youtu.be/BHS-_AXCWrc?si=mAEfBZWMREXhzzUg",
    "seasonYear": 2026,
    "season": "SUMMER"
  },
  {
    "reddit_title": "Magilumiere Magical Girls Inc. Season 2 • Kabushikigaisha Magi-Lumière Season 2 - Episode 2 discussion",
    "matched_anime_id": 185692,
    "matched_anime_native": "株式会社マジルミエ 第2期",
    "score": 100.0,
    "num_comments": 58,
    "url": "https://www.reddit.com/r/anime/comments/1utt17d/magilumiere_magical_girls_inc_season_2/",
    "seasonYear": 2026,
    "season": "SUMMER"
  },
  {
    "reddit_title": "Hanaori-san Still Wants to Fight in the Next Life • Hanaori-san wa Tensei Shite mo Kenka ga Shitai - Episode 1 discussion",
    "matched_anime_id": 199066,
    "matched_anime_native": "花織さんは転生しても喧嘩がしたい",
    "score": 100.0,
    "num_comments": 151,
    "url": "https://www.reddit.com/r/anime/comments/1utqdn5/hanaorisan_still_wants_to_fight_in_the_next_life/",
    "seasonYear": 2026,
    "season": "SUMMER"
  },
  {
    "reddit_title": "Grow Up Show: Sunflower Circus • Grow Up Show: Himawari no Circus-dan - Episode 2 discussion",
    "matched_anime_id": 196017,
    "matched_anime_native": "グロウアップショウ ～ひまわりのサーカス団～",
    "score": 100.0,
    "num_comments": 74,
    "url": "https://www.reddit.com/r/anime/comments/1utoajx/grow_up_show_sunflower_circus_grow_up_show/",
    "seasonYear": 2026,
    "season": "SUMMER"
  },
  {
    "reddit_title": "Magical Girl Lyrical Nanoha EXCEEDS Gun Blaze Vengeance • Mahou Shoujo Lyrical Nanoha EXCEEDS: Gun Blaze Vengeance - Episode 2 discussion",
    "matched_anime_id": 185875,
    "matched_anime_native": "魔法少女リリカルなのは EXCEEDS Gun Blaze Vengeance",
    "score": 100.0,
    "num_comments": 101,
    "url": "https://www.reddit.com/r/anime/comments/1utpk39/magical_girl_lyrical_nanoha_exceeds_gun_blaze/",
    "seasonYear": 2026,
    "season": "SUMMER"
  },
  {
    "reddit_title": "The Ghost in the Shell (2026) Opening - Violin Cover",
    "matched_anime_id": 177699,
    "matched_anime_native": "攻殻機動隊 THE GHOST IN THE SHELL",
    "score": 100.0,
    "num_comments": 7,
    "url": "https://v.redd.it/uwieiyhl1och1",
    "seasonYear": 2026,
    "season": "SUMMER"
  },
  {
    "reddit_title": "The Cat and the Dragon • Neko to Ryuu - Episode 3 discussion",
    "matched_anime_id": 186863,
    "matched_anime_native": "猫と竜",
    "score": 100.0,
    "num_comments": 119,
    "url": "https://www.reddit.com/r/anime/comments/1utk7vc/the_cat_and_the_dragon_neko_to_ryuu_episode_3/",
    "seasonYear": 2026,
    "season": "SUMMER"
  },
  {
    "reddit_title": "Ascendance of a Bookworm: Adopted Daughter of an Archduke • Honzuki no Gekokujou: Shisho ni Naru Tame ni wa Shudan wo Erandeiraremasen - Ryushu no Youjo - Episode 13 discussion",
    "matched_anime_id": 171110,
    "matched_anime_native": "本好きの下剋上 領主の養女",
    "score": 100.0,
    "num_comments": 295,
    "url": "https://www.reddit.com/r/anime/comments/1utfika/ascendance_of_a_bookworm_adopted_daughter_of_an/",
    "seasonYear": 2026,
    "season": "SPRING"
  },
  {
    "reddit_title": "Black Torch - Episode 2 discussion",
    "matched_anime_id": 187538,
    "matched_anime_native": "BLACK TORCH",
    "score": 100.0,
    "num_comments": 130,
    "url": "https://www.reddit.com/r/anime/comments/1utjnk0/black_torch_episode_2_discussion/",
    "seasonYear": 2026,
    "season": "SUMMER"
  },
  {
    "reddit_title": "Any Ultrakill animes out there?",
    "matched_anime_id": 198113,
    "matched_anime_native": "キルアオ",
    "score": 85.71428571428572,
    "num_comments": 2,
    "url": "https://www.reddit.com/r/anime/comments/1uuy150/any_ultrakill_animes_out_there/",
    "seasonYear": 2026,
    "season": "SPRING"
  }
]